torcwa/__init__.py
torcwa/geometry.py
torcwa/rcwa.py
torcwa/torch_eig.py
torcwa-0.1.4.2.dist-info/LICENSE
torcwa-0.1.4.2.dist-info/METADATA
torcwa-0.1.4.2.dist-info/WHEEL
torcwa-0.1.4.2.dist-info/dependency_links.txt
torcwa-0.1.4.2.dist-info/top_level.txt
torcwa-0.1.4.2.dist-info/RECORD
